UartStates.vh
// states of state machine
`define RESET     3'b000
`define IDLE      3'b001
`define START_BIT 3'b010
`define DATA_BITS 3'b011
`define STOP_BIT  3'b100
`define READY     3'b101 // receiver only

Uart8Transmitter.v
`include "UartStates.vh"

/*
 * 8-bit UART Transmitter
 *
 * Able to transmit 8 bits of serial data, one start bit, one stop bit
 *
 * When transmit is in progress over {out}, {busy} is driven high
 *
 * When transmit is complete, {done} is driven high for one tx clock cycle
 *
 * Capable of back-to-back transmits for full bandwidth utilization,
 *   by only changing the {in} data
 *   (*change before {done} rising edge)
 *
 * Finer control over when to start the next frame is provided by cycling
 *   the {start} input low then high
 *
 * System clock must be divided down to the baud rate, which is the
 *   {clk} input
 *
 * {TURBO_FRAMES}: performance mode versus forgiving mode:
 *
 * 0: forgiving mode:
 *    drive the mark state, aka stop bit, output high for two
 *    tx clock cycles instead of one - this way, the boundaries between
 *    data frames are distinguished in the transmitted data stream,
 *    for more robust sync between tx/rx
 *    (*sync can be re-established more quickly if it's lost)
 *    (*this mode will only have an effect in the max, back-to-back,
 *     frame transmission use case)
 *    (*this mode has no positive effect in an environment of
 *     reliably matched tx/rx baud clocks)
 *
 * 1: performance mode:
 *    drive the mark state output high for one cycle when at max rate
 *    (*this is the normal UART protocol: 80% effective data rate
 *     for 8 bits in a frame, no parity)
 */
module Uart8Transmitter #(
    parameter TURBO_FRAMES = 0
)(
    input wire clk,      // baud rate
    input wire en,
    input wire start,    // start transmission
    input wire [7:0] in, // parallel data to transmit
    output reg busy,     // transmit is in progress
    output reg done,     // end of transmission
    output reg out       // tx line for serial data
);

reg [2:0] state     = `RESET;
reg [7:0] in_data   = 8'b0; // shift reg for the data to transmit serially
reg [2:0] bit_index = 3'b0; // index for 8-bit data

always @(posedge clk) begin
    /*
     * Disable at any time in the flow
     */
    if (!en) begin
        state <= `RESET;
    end

    /*
     * State machine
     */
    case (state)
        `RESET: begin
            // state variables
            bit_index <= 3'b0;
            // outputs
            busy      <= 1'b0;
            done      <= 1'b0;
            out       <= 1'b1; // drive the line high for IDLE state
            // next state
            if (en) begin
                state <= `IDLE;
            end
        end

        `IDLE: begin
            if (start) begin
                in_data <= in; // register the input data
                state   <= `START_BIT;
            end
        end

        `START_BIT: begin
            bit_index <= 3'b0;
            busy      <= 1'b1;
            done      <= 1'b0;
            out       <= 1'b0; // send the space output, aka start bit (low)
            state     <= `DATA_BITS;
        end

        `DATA_BITS: begin // take 8 clock cycles for data bits to be sent
            // grab each input bit using a shift register: the hardware
            // realization is simple compared to routing the access
            // dynamically, i.e. using in_data[bit_index]
            in_data   <= { 1'b0, in_data[7:1] };
            out       <= in_data[0];
            // manage the state transition
            bit_index <= bit_index + 3'b1;
            if (&bit_index) begin
                // bit_index wraps around to zero
                state <= `STOP_BIT;
            end
        end

        `STOP_BIT: begin
            done              <= 1'b1; // signal the transmission stop
            out               <= 1'b1; // transition to mark state output (high)
            if (start) begin
                if (done == 1'b0) begin // this distinguishes 2 sub-states
                    in_data   <= in; // register new input data
                    if (TURBO_FRAMES) begin
                        state <= `START_BIT; // go direct to transmit
                    end else begin
                        state <= `STOP_BIT; // keep mark state one extra cycle
                    end
                end else begin // there was extra cycle within this state
                    done      <= 1'b0;
                    state     <= `START_BIT; // now go to transmit
                end
            end else begin
                state         <= `RESET;
            end
        end

        default: begin
            state <= `RESET;
        end
    endcase
end

endmodule

Uart8Receiver.v
`include "UartStates.vh"

/*
 * 8-bit UART Receiver
 *
 * Able to receive 8 bits of serial data, one start bit, one stop bit
 *
 * When receive is detected and in progress over {in}, {busy} is driven high
 *
 * When receive is complete, {done} is driven high for one serial bit cycle
 *   (aka baud interval: equal to 16 {clk} ticks)
 *
 * Output data should be taken away within one baud interval or it will be lost
 *
 * System clock must be divided down to oversampling rate times baud rate
 *   to provide the {clk} input
 *
 * (*Note this module's logic is hard-coded based on 16x oversampling rate)
 */
module Uart8Receiver (
    input wire clk,      // rx data sampling rate
    input wire en,
    input wire in,       // rx line
    output reg busy,     // transaction is in progress
    output reg done,     // end of transaction
    output reg err,      // error while receiving data
    output reg [7:0] out // the received data assembled in parallel form
);

reg [2:0] state          = `RESET;
reg [1:0] in_reg         = 2'b0; // shift reg for input signal conditioning
reg [4:0] in_hold_reg    = 5'b0; // shift reg for signal hold time checks
reg [3:0] sample_count   = 4'b0; // count ticks for 16x oversample
reg [4:0] out_hold_count = 5'b0; // count ticks before clearing output data
reg [2:0] bit_index      = 3'b0; // index for 8-bit data
reg [7:0] received_data  = 8'b0; // shift reg for the deserialized data
wire in_sample;
wire [3:0] in_prior_hold_reg;
wire [3:0] in_current_hold_reg;

/*
 * Double-register the incoming data:
 *
 * This prevents metastability problems crossing into rx clock domain
 *
 * After registering, only the in_sample wire is to be accessed - the
 *   earlier, unconditioned signal {in} must be ignored
 */
always @(posedge clk) begin
    in_reg <= { in_reg[0], in };
end

assign in_sample = in_reg[1];

/*
 * Track the incoming data for 4 rx {clk} ticks + 1, to be able to enforce a
 *   minimum hold time of 4 {clk} ticks for any rx signal
 */
always @(posedge clk) begin
    in_hold_reg <= { in_hold_reg[3:1], in_sample, in_reg[0] };
end

assign in_prior_hold_reg   = in_hold_reg[4:1];
assign in_current_hold_reg = in_hold_reg[3:0];

always @(posedge clk) begin
    /*
     * End the validity of output data after precise time of one serial bit cycle:
     *
     * Output signals from this module might as well be consistent with input
     *   rate, which is the baud rate
     *
     * This hold is for the case when detection of a next transmit cut the
     *   prior stop and ready transitions short; i.e. IDLE state has been entered
     *   direct from STOP_BIT state or READY state
     */
    if (|out_hold_count) begin
        out_hold_count     <= out_hold_count + 5'b1;
        if (out_hold_count == 5'b10000) begin // reached 16 -
            // timed output interval ends
            out_hold_count <= 5'b0;
            done           <= 1'b0;
            out            <= 8'b0;
        end
    end

    /*
     * Disable at any time in the flow
     */
    if (!en) begin
        state <= `RESET;
    end

    /*
     * State machine
     */
    case (state)
        `RESET: begin
            // state variables
            sample_count   <= 4'b0;
            out_hold_count <= 5'b0;
            received_data  <= 8'b0;
            // outputs
            busy           <= 1'b0;
            done           <= 1'b0;
            if (en && err && !in_sample) begin // in error condition already -
                // leave the output uninterrupted
                err        <= 1'b1;
            end else begin
                err        <= 1'b0;
            end
            out            <= 8'b0; // output parallel data only during {done}
            // next state
            if (en) begin
                state      <= `IDLE;
            end
        end

        `IDLE: begin
            /*
             * Accept low-going input as the trigger to start:
             *
             * Count from the first low sample, and sample again at the
             *   mid-point of a full baud interval to accept the low signal
             *
             * Then start the count for the proceeding full baud intervals
             */
            if (!in_sample) begin
                if (sample_count == 4'b0) begin
                    if (&in_prior_hold_reg || done && !err) begin
                        // meets the preceding min high hold time -
                        // note that {done} && !{err} encodes the fact that
                        // the min hold time was met earlier in STOP_BIT state
                        // or READY state
                        sample_count  <= 4'b1;
                        err           <= 1'b0;
                    end else begin
                        // this was a false start -
                        // remain in IDLE state with sample_count zero
                        err           <= 1'b1;
                    end
                end else begin
                    sample_count      <= sample_count + 4'b1;
                    if (sample_count == 4'b1100) begin // reached 12
                        // start signal meets an additional hold time
                        // of >= 4 rx ticks after its own mid-point -
                        // start new full interval count but from the mid-point
                        sample_count  <= 4'b0100;
                        busy          <= 1'b1;
                        err           <= 1'b0;
                        state         <= `START_BIT;
                    end
                end
            end else if (|sample_count) begin
                // bit did not remain low while waiting till 8 then 12 -
                // remain in IDLE state
                sample_count          <= 4'b0;
                received_data         <= 8'b0;
                err                   <= 1'b1;
            end
        end

        `START_BIT: begin
            /*
             * Wait one full baud interval to the mid-point of first bit
             */
            sample_count      <= sample_count + 4'b1;
            if (&sample_count) begin // reached 15
                // sample_count wraps around to zero
                bit_index     <= 3'b1;
                received_data <= { in_sample, 7'b0 };
                out           <= 8'b0;
                state         <= `DATA_BITS;
            end
        end

        `DATA_BITS: begin
            /*
             * Take 8 baud intervals to receive serial data
             */
            sample_count      <= sample_count + 4'b1;
            if (&sample_count) begin // reached 15 - save one more bit of data
                // store the bit using a shift register: the hardware
                // realization is simple compared to routing the bit
                // dynamically, i.e. using received_data[bit_index]
                received_data <= { in_sample, received_data[7:1] };
                // manage the state transition
                bit_index     <= bit_index + 3'b1;
                if (&bit_index) begin
                    // bit_index wraps around to zero
                    // sample_count wraps around to zero
                    state     <= `STOP_BIT;
                end
            end
        end

        `STOP_BIT: begin
            /*
             * Accept the received data if input goes high:
             *
             * If stop signal condition(s) met, drive the {done} signal high
             *   for one bit cycle
             *
             * Otherwise drive the {err} signal high for one bit cycle
             *
             * Since this baud clock may not track the transmitter baud clock
             *   precisely in reality, accept the transition to handling the
             *   next start bit any time after the stop bit mid-point
             */
            sample_count               <= sample_count + 4'b1;
            if (sample_count[3]) begin // reached 8 to 15
                if (!in_sample) begin
                    // accept that transmit has completed only if the stop
                    // signal held for a time of >= 4 rx ticks before it
                    // changed to a start signal
                    if (sample_count == 4'b1000 &&
                            &in_prior_hold_reg) begin // meets the hold time
                        // can accept the transmitted data and output it
                        sample_count   <= 4'b0;
                        out_hold_count <= 5'b1;
                        done           <= 1'b1;
                        out            <= received_data;
                        state          <= `IDLE;
                    end else if (&sample_count) begin // reached 15
                        // bit did not go high or remain high -
                        // signal {err}, continuing until condition resolved
                        sample_count   <= 4'b0;
                        received_data  <= 8'b0;
                        busy           <= 1'b0;
                        err            <= 1'b1;
                        state          <= `IDLE;
                    end
                end else begin
                    if (&in_current_hold_reg) begin // meets min high hold time
                        // can accept the transmitted data and output it
                        sample_count   <= 4'b0;
                        done           <= 1'b1;
                        out            <= received_data;
                        state          <= `READY;
                    end else if (&sample_count) begin // reached 15
                        // did not meet min high hold time -
                        // signal {err} for this transmit
                        sample_count   <= 4'b0;
                        err            <= 1'b1;
                        state          <= `READY;
                    end
                end
            end
        end

        `READY: begin
            /*
             * Wait one full bit cycle to sustain the {out} data, the
             *   {done} signal or the {err} signal
             */
            sample_count              <= sample_count + 4'b1;
            if (!err && !in_sample || &sample_count) begin
                // check if this is the change to a start signal -
                // note that in this state, in_sample has met the min high
                // hold time any time it drops to low
                // (also in these cases, namely !{err} or tick 15 special case,
                //  signaling of {done} is in progress)
                if (&sample_count) begin // reached 15, last tick, and no error
                    // (signaling of {done} is now complete)
                    if (in_sample) begin
                        // not transitioning to start bit -
                        // sample_count wraps around to zero
                        received_data <= 8'b0;
                        busy          <= 1'b0;
                    end else begin
                        // transitioning to start bit -
                        // sustain the {busy} signal high
                        sample_count  <= 4'b1;
                    end
                    done              <= 1'b0;
                    out               <= 8'b0;
                    state             <= `IDLE;
                end else begin
                    // in_sample drops from high to low
                    // (signaling of {done} continues)
                    sample_count      <= 4'b1;
                    // continue the counting
                    out_hold_count    <= sample_count + 5'b00010;
                    state             <= `IDLE;
                end
            end else if (&sample_count[3:1]) begin // reached 14 -
                // additional tick 15 comes from transiting the READY state
                // to get to the RESET state
                if (err || !in_sample) begin
                    state             <= `RESET;
                end
                // otherwise, signaling of {done} is in progress (i.e. !{err}) -
                // in this case, on tick 15, will be checking if in_sample
                // dropped from high to low on the entry to IDLE state
            end
        end

        default: begin
            state <= `RESET;
        end
    endcase
end

endmodule

BaudRateGenerator.v
/*
 * Baud rate generator to divide {CLOCK_RATE} (internal system clock) into
 *   {BAUD_RATE} tx/rx pair, with rx oversample by default 16x
 */
module BaudRateGenerator #(
    parameter CLOCK_RATE         = 100000000, // board clock (default 100MHz)
    parameter BAUD_RATE          = 9600,
    parameter RX_OVERSAMPLE_RATE = 16
)(
    input wire clk,   // board clock (*note: at the {CLOCK_RATE} rate)
    output reg rxClk, // baud rate for rx
    output reg txClk  // baud rate for tx
);

localparam RX_ACC_MAX   = CLOCK_RATE / (2 * BAUD_RATE * RX_OVERSAMPLE_RATE);
localparam TX_ACC_MAX   = CLOCK_RATE / (2 * BAUD_RATE);
localparam RX_ACC_WIDTH = $clog2(RX_ACC_MAX);
localparam TX_ACC_WIDTH = $clog2(TX_ACC_MAX);

reg [RX_ACC_WIDTH-1:0] rx_counter = 0;
reg [TX_ACC_WIDTH-1:0] tx_counter = 0;

initial begin
    rxClk = 1'b0;
    txClk = 1'b0;
end

always @(posedge clk) begin
    // rx clock
    if (rx_counter == RX_ACC_MAX[RX_ACC_WIDTH-1:0]) begin
        rx_counter <= 0;
        rxClk      <= ~rxClk;
    end else begin
        rx_counter <= rx_counter + 1'b1;
    end

    // tx clock
    if (tx_counter == TX_ACC_MAX[TX_ACC_WIDTH-1:0]) begin
        tx_counter <= 0;
        txClk      <= ~txClk;
    end else begin
        tx_counter <= tx_counter + 1'b1;
    end
end

endmodule

Uart8.v
`include "BaudRateGenerator.v"
`include "Uart8Receiver.v"
`include "Uart8Transmitter.v"

/*
 * Simple 8-bit UART realization
 *
 * Able to transmit and receive 8 bits of serial data, one start bit,
 *   one stop bit
 */
module Uart8 #(
    parameter CLOCK_RATE   = 100000000, // board clock (default 100MHz)
    parameter BAUD_RATE    = 9600,
    parameter TURBO_FRAMES = 0          // see Uart8Transmitter
)(
    input wire clk, // board clock (*note: at the {CLOCK_RATE} rate)

    // rx interface
    input wire rxEn,
    input wire rx,
    output wire rxBusy,
    output wire rxDone,
    output wire rxErr,
    output wire [7:0] out,

    // tx interface
    input wire txEn,
    input wire txStart,
    input wire [7:0] in,
    output wire txBusy,
    output wire txDone,
    output wire tx
);

// this value cannot be changed in the current implementation
localparam RX_OVERSAMPLE_RATE = 16;

wire rxClk;
wire txClk;

BaudRateGenerator #(
    .CLOCK_RATE(CLOCK_RATE),
    .BAUD_RATE(BAUD_RATE),
    .RX_OVERSAMPLE_RATE(RX_OVERSAMPLE_RATE)
) generatorInst (
    .clk(clk),
    .rxClk(rxClk),
    .txClk(txClk)
);

Uart8Receiver rxInst (
    .clk(rxClk),
    .en(rxEn),
    .in(rx),
    .busy(rxBusy),
    .done(rxDone),
    .err(rxErr),
    .out(out)
);

Uart8Transmitter #(
    .TURBO_FRAMES(TURBO_FRAMES)
) txInst (
    .clk(txClk),
    .en(txEn),
    .start(txStart),
    .in(in),
    .busy(txBusy),
    .done(txDone),
    .out(tx)
);

endmodule

tests/12.v
`timescale 100ns/1ns
`default_nettype none

`include "Uart8.v"

module test;

localparam CLOCK_FREQ = 12000000; // Alhambra board
localparam SIM_STEP_FREQ = 1 / 0.0000001 / 2; // this sim timescale 100ns

// for the simulation timeline:
// ratio SIM_STEP_FREQ MHz / CLOCK_FREQ MHz gives the output waveform in proper time
// (*but note all clocks and the timeline are approximate due to rounding)
localparam SIM_TIMESTEP_FACTOR = SIM_STEP_FREQ / CLOCK_FREQ;

localparam ENABLED_BAUD_CLOCK_STEPS = 13;

reg        clk;
reg        en_1;
reg        en_2;
reg        txStart_1;
reg        txStart_2;
wire       txBusy_1;
wire       txBusy_2;
wire       rxBusy_1;
wire       rxBusy_2;
wire       txDone_1;
wire       txDone_2;
wire       rxDone_1;
wire       rxDone_2;
wire       rxErr_1;
wire       rxErr_2;
reg [7:0]  txByte_1;
reg [7:0]  txByte_2;
wire [7:0] rxByte_1;
wire [7:0] rxByte_2;
wire       bus_wire_1_2;
wire       bus_wire_2_1;
integer c;

Uart8 #(.CLOCK_RATE(CLOCK_FREQ), .TURBO_FRAMES(1)) uart1(
  .clk(clk),

  // rx interface
  .rxEn(en_2),
  .rx(bus_wire_2_1),
  .rxBusy(rxBusy_1),
  .rxDone(rxDone_1),
  .rxErr(rxErr_1),
  .out(rxByte_1),

  // tx interface
  .txEn(en_1),
  .txStart(txStart_1),
  .in(txByte_1),
  .txBusy(txBusy_1),
  .txDone(txDone_1),
  .tx(bus_wire_1_2)
);

Uart8 #(.CLOCK_RATE(CLOCK_FREQ)) uart2(
  .clk(clk),

  // rx interface
  .rxEn(en_1),
  .rx(bus_wire_1_2),
  .rxBusy(rxBusy_2),
  .rxDone(rxDone_2),
  .rxErr(rxErr_2),
  .out(rxByte_2),

  // tx interface
  .txEn(en_2),
  .txStart(txStart_2),
  .in(txByte_2),
  .txBusy(txBusy_2),
  .txDone(txDone_2),
  .tx(bus_wire_2_1)
);

initial clk = 1'b0;

always #SIM_TIMESTEP_FACTOR clk = ~clk;

initial c = 1;

always @(posedge uart1.txClk) begin
  // drive the start signal low synchronously from the second last rx done signal
  if (rxDone_2) begin
    c <= c + 1;
    if (c < 2) begin
      txStart_1 <= 1'b0;
    end
  end
end

initial begin
  integer t;

  $dumpfile(`DUMP_FILE_NAME);
  $dumpvars(0, test);

#600
  en_1 = 1'b0;
  txStart_1 = 1'b0;
#600
  en_1 = 1'b1;
  txStart_1 = 1'b1;
#600
  txByte_1 = 8'b01111010;

  $display("%7.2fms | tx start: %d", $realtime/10000, txStart_1);
  $display("%7.2fms | tx data: %8b", $realtime/10000, txByte_1);

  for (t = 0; t < ENABLED_BAUD_CLOCK_STEPS; t++) begin
    // #1000 x 100ns == 0.1ms == 1 tx clock period (approximately) at 9600 baud
#1000
    case (t)
      10: begin
        // before the high-going done signal (so that the IDLE and START_BIT states
        // are not entered with the existing data at tx in)
        txByte_1 = 8'b10110001;

        $display("%7.2fms | tx data: %8b", $realtime/10000, txByte_1);
        $display("%7.2fms | rx done: %d", $realtime/10000, rxDone_2);
        $display("%7.2fms | rx data: %8b", $realtime/10000, rxByte_2);
      end
    endcase
  end

  $display("%7.2fms | rx done: %d", $realtime/10000, rxDone_2);
  $display("%7.2fms | rx data: %8b", $realtime/10000, rxByte_2);

  for (t = 0; t < ENABLED_BAUD_CLOCK_STEPS; t++) begin
#1000
    case (t)
      5: begin
        txStart_1 = 1'b0;

        $display("%7.2fms | tx start: %d", $realtime/10000, txStart_1);
        $display("%7.2fms | rx done: %d", $realtime/10000, rxDone_2);
        $display("%7.2fms | rx data: %8b", $realtime/10000, rxByte_2);
      end
      10: begin
        // output is ready

        $display("%7.2fms | tx start: %d", $realtime/10000, txStart_1);
        $display("%7.2fms | rx done: %d", $realtime/10000, rxDone_2);
        $display("%7.2fms | rx data: %8b", $realtime/10000, rxByte_2);
      end
    endcase
  end

#1100
  en_1 = 1'b0;
#2800

  $finish();
end

endmodule

tests/11.vcd
$date
	Thu Jan 05 22:45:11 2023
$end
$version
	Icarus Verilog
$end
$timescale
	1ns
$end
$scope module test $end
$var wire 1 ! txDone_2 $end
$var wire 1 " txDone_1 $end
$var wire 1 # txBusy_2 $end
$var wire 1 $ txBusy_1 $end
$var wire 1 % rxErr_2 $end
$var wire 1 & rxErr_1 $end
$var wire 1 ' rxDone_2 $end
$var wire 1 ( rxDone_1 $end
$var wire 8 ) rxByte_2 [7:0] $end
$var wire 8 * rxByte_1 [7:0] $end
$var wire 1 + rxBusy_2 $end
$var wire 1 , rxBusy_1 $end
$var wire 1 - bus_wire_2_1 $end
$var wire 1 . bus_wire_1_2 $end
$var reg 1 / clk $end
$var reg 1 0 en_1 $end
$var reg 1 1 en_2 $end
$var reg 8 2 txByte_1 [7:0] $end
$var reg 8 3 txByte_2 [7:0] $end
$var reg 1 4 txStart_1 $end
$var reg 1 5 txStart_2 $end
$var integer 32 6 c [31:0] $end
$scope module uart1 $end
$var wire 1 / clk $end
$var wire 8 7 in [7:0] $end
$var wire 1 1 rxEn $end
$var wire 1 0 txEn $end
$var wire 1 4 txStart $end
$var wire 1 " txDone $end
$var wire 1 8 txClk $end
$var wire 1 $ txBusy $end
$var wire 1 . tx $end
$var wire 1 & rxErr $end
$var wire 1 ( rxDone $end
$var wire 1 9 rxClk $end
$var wire 1 , rxBusy $end
$var wire 1 - rx $end
$var wire 8 : out [7:0] $end
$scope module generatorInst $end
$var wire 1 / clk $end
$var reg 1 9 rxClk $end
$var reg 6 ; rx_counter [5:0] $end
$var reg 1 8 txClk $end
$var reg 10 < tx_counter [9:0] $end
$upscope $end
$scope module rxInst $end
$var wire 1 9 clk $end
$var wire 1 1 en $end
$var wire 1 = in_sample $end
$var wire 4 > in_prior_hold_reg [3:0] $end
$var wire 4 ? in_current_hold_reg [3:0] $end
$var wire 1 - in $end
$var reg 3 @ bit_index [2:0] $end
$var reg 1 , busy $end
$var reg 1 ( done $end
$var reg 1 & err $end
$var reg 5 A in_hold_reg [4:0] $end
$var reg 2 B in_reg [1:0] $end
$var reg 8 C out [7:0] $end
$var reg 5 D out_hold_count [4:0] $end
$var reg 8 E received_data [7:0] $end
$var reg 4 F sample_count [3:0] $end
$var reg 3 G state [2:0] $end
$upscope $end
$scope module txInst $end
$var wire 1 8 clk $end
$var wire 1 0 en $end
$var wire 8 H in [7:0] $end
$var wire 1 4 start $end
$var reg 3 I bit_index [2:0] $end
$var reg 1 $ busy $end
$var reg 1 " done $end
$var reg 8 J in_data [7:0] $end
$var reg 1 . out $end
$var reg 3 K state [2:0] $end
$upscope $end
$upscope $end
$scope module uart2 $end
$var wire 1 / clk $end
$var wire 8 L in [7:0] $end
$var wire 1 . rx $end
$var wire 1 0 rxEn $end
$var wire 1 1 txEn $end
$var wire 1 5 txStart $end
$var wire 1 ! txDone $end
$var wire 1 M txClk $end
$var wire 1 # txBusy $end
$var wire 1 - tx $end
$var wire 1 % rxErr $end
$var wire 1 ' rxDone $end
$var wire 1 N rxClk $end
$var wire 1 + rxBusy $end
$var wire 8 O out [7:0] $end
$scope module generatorInst $end
$var wire 1 / clk $end
$var reg 1 N rxClk $end
$var reg 6 P rx_counter [5:0] $end
$var reg 1 M txClk $end
$var reg 10 Q tx_counter [9:0] $end
$upscope $end
$scope module rxInst $end
$var wire 1 N clk $end
$var wire 1 0 en $end
$var wire 1 . in $end
$var wire 1 R in_sample $end
$var wire 4 S in_prior_hold_reg [3:0] $end
$var wire 4 T in_current_hold_reg [3:0] $end
$var reg 3 U bit_index [2:0] $end
$var reg 1 + busy $end
$var reg 1 ' done $end
$var reg 1 % err $end
$var reg 5 V in_hold_reg [4:0] $end
$var reg 2 W in_reg [1:0] $end
$var reg 8 X out [7:0] $end
$var reg 5 Y out_hold_count [4:0] $end
$var reg 8 Z received_data [7:0] $end
$var reg 4 [ sample_count [3:0] $end
$var reg 3 \ state [2:0] $end
$upscope $end
$scope module txInst $end
$var wire 1 M clk $end
$var wire 1 1 en $end
$var wire 8 ] in [7:0] $end
$var wire 1 5 start $end
$var reg 3 ^ bit_index [2:0] $end
$var reg 1 # busy $end
$var reg 1 ! done $end
$var reg 8 _ in_data [7:0] $end
$var reg 1 - out $end
$var reg 3 ` state [2:0] $end
$upscope $end
$upscope $end
$scope begin $unm_blk_70 $end
$var integer 32 a t [31:0] $end
$upscope $end
$upscope $end
$enddefinitions $end
#0
$dumpvars
bx a
b0 `
b0 _
b0 ^
bx ]
b0 \
b0 [
b0 Z
b0 Y
bx X
b0 W
b0 V
b0 U
b0 T
b0 S
0R
b0 Q
b0 P
bx O
0N
0M
bx L
b0 K
b0 J
b0 I
bx H
b0 G
b0 F
b0 E
b0 D
bx C
b0 B
b0 A
b0 @
b0 ?
b0 >
0=
b0 <
b0 ;
bx :
09
08
bx 7
b1 6
x5
x4
bx 3
bx 2
x1
x0
0/
x.
x-
x,
x+
bx *
bx )
x(
x'
x&
x%
x$
x#
x"
x!
$end
#42
b1 <
b1 ;
b1 Q
b1 P
1/
#84
0/
#126
b10 Q
b10 P
b10 <
b10 ;
1/
#168
0/
#210
b11 <
b11 ;
b11 Q
b11 P
1/
#252
0/
#294
b100 Q
b100 P
b100 <
b100 ;
1/
#336
0/
#378
b101 <
b101 ;
b101 Q
b101 P
1/
#420
0/
#462
b110 Q
b110 P
b110 <
b110 ;
1/
#504
0/
#546
b111 <
b111 ;
b111 Q
b111 P
1/
#588
0/
#630
b1000 Q
b1000 P
b1000 <
b1000 ;
1/
#672
0/
#714
b1001 <
b1001 ;
b1001 Q
b1001 P
1/
#756
0/
#798
b1010 Q
b1010 P
b1010 <
b1010 ;
1/
#840
0/
#882
b1011 <
b1011 ;
b1011 Q
b1011 P
1/
#924
0/
#966
b1100 Q
b1100 P
b1100 <
b1100 ;
1/
#1008
0/
#1050
b1101 <
b1101 ;
b1101 Q
b1101 P
1/
#1092
0/
#1134
b1110 Q
b1110 P
b1110 <
b1110 ;
1/
#1176
0/
#1218
b1111 <
b1111 ;
b1111 Q
b1111 P
1/
#1260
0/
#1302
b10000 Q
b10000 P
b10000 <
b10000 ;
1/
#1344
0/
#1386
b10001 <
b10001 ;
b10001 Q
b10001 P
1/
#1428
0/
#1470
b10010 Q
b10010 P
b10010 <
b10010 ;
1/
#1512
0/
#1554
b10011 <
b10011 ;
b10011 Q
b10011 P
1/
#1596
0/
#1638
b10100 Q
b10100 P
b10100 <
b10100 ;
1/
#1680
0/
#1722
b10101 <
b10101 ;
b10101 Q
b10101 P
1/
#1764
0/
#1806
b10110 Q
b10110 P
b10110 <
b10110 ;
1/
#1848
0/
#1890
b10111 <
b10111 ;
b10111 Q
b10111 P
1/
#1932
0/
#1974
b11000 Q
b11000 P
b11000 <
b11000 ;
1/
#2016
0/
#2058
b11001 <
b11001 ;
b11001 Q
b11001 P
1/
#2100
0/
#2142
b11010 Q
b11010 P
b11010 <
b11010 ;
1/
#2184
0/
#2226
b11011 <
b11011 ;
b11011 Q
b11011 P
1/
#2268
0/
#2310
b11100 Q
b11100 P
b11100 <
b11100 ;
1/
#2352
0/
#2394
b11101 <
b11101 ;
b11101 Q
b11101 P
1/
#2436
0/
#2478
b11110 Q
b11110 P
b11110 <
b11110 ;
1/
#2520
0/
#2562
b11111 <
b11111 ;
b11111 Q
b11111 P
1/
#2604
0/
#2646
b100000 Q
b100000 P
b100000 <
b100000 ;
1/
#2688
0/
#2730
b100001 <
b100001 ;
b100001 Q
b100001 P
1/
#2772
0/
#2814
b100010 Q
b100010 P
b100010 <
b100010 ;
1/
#2856
0/
#2898
b100011 <
b100011 ;
b100011 Q
b100011 P
1/
#2940
0/
#2982
b100100 Q
b100100 P
b100100 <
b100100 ;
1/
#3024
0/
#3066
b100101 <
b100101 ;
b100101 Q
b100101 P
1/
#3108
0/
#3150
b100110 Q
b100110 P
b100110 <
b100110 ;
1/
#3192
0/
#3234
b100111 <
b100111 ;
b100111 Q
b100111 P
1/
#3276
0/
#3318
b0x W
b0 )
b0 O
b0 X
0%
0'
0+
b0x B
b0 *
b0 :
b0 C
0&
0(
0,
b101000 Q
1N
b0 P
b101000 <
19
b0 ;
1/
#3360
0/
#3402
b101001 <
b1 ;
b101001 Q
b1 P
1/
#3444
0/
#3486
b101010 Q
b10 P
b101010 <
b10 ;
1/
#3528
0/
#3570
b101011 <
b11 ;
b101011 Q
b11 P
1/
#3612
0/
#3654
b101100 Q
b100 P
b101100 <
b100 ;
1/
#3696
0/
#3738
b101101 <
b101 ;
b101101 Q
b101 P
1/
#3780
0/
#3822
b101110 Q
b110 P
b101110 <
b110 ;
1/
#3864
0/
#3906
b101111 <
b111 ;
b101111 Q
b111 P
1/
#3948
0/
#3990
b110000 Q
b1000 P
b110000 <
b1000 ;
1/
#4032
0/
#4074
b110001 <
b1001 ;
b110001 Q
b1001 P
1/
#4116
0/
#4158
b110010 Q
b1010 P
b110010 <
b1010 ;
1/
#4200
0/
#4242
b110011 <
b1011 ;
b110011 Q
b1011 P
1/
#4284
0/
#4326
b110100 Q
b1100 P
b110100 <
b1100 ;
1/
#4368
0/
#4410
b110101 <
b1101 ;
b110101 Q
b1101 P
1/
#4452
0/
#4494
b110110 Q
b1110 P
b110110 <
b1110 ;
1/
#4536
0/
#4578
b110111 <
b1111 ;
b110111 Q
b1111 P
1/
#4620
0/
#4662
b111000 Q
b10000 P
b111000 <
b10000 ;
1/
#4704
0/
#4746
b111001 <
b10001 ;
b111001 Q
b10001 P
1/
#4788
0/
#4830
b111010 Q
b10010 P
b111010 <
b10010 ;
1/
#4872
0/
#4914
b111011 <
b10011 ;
b111011 Q
b10011 P
1/
#4956
0/
#4998
b111100 Q
b10100 P
b111100 <
b10100 ;
1/
#5040
0/
#5082
b111101 <
b10101 ;
b111101 Q
b10101 P
1/
#5124
0/
#5166
b111110 Q
b10110 P
b111110 <
b10110 ;
1/
#5208
0/
#5250
b111111 <
b10111 ;
b111111 Q
b10111 P
1/
#5292
0/
#5334
b1000000 Q
b11000 P
b1000000 <
b11000 ;
1/
#5376
0/
#5418
b1000001 <
b11001 ;
b1000001 Q
b11001 P
1/
#5460
0/
#5502
b1000010 Q
b11010 P
b1000010 <
b11010 ;
1/
#5544
0/
#5586
b1000011 <
b11011 ;
b1000011 Q
b11011 P
1/
#5628
0/
#5670
b1000100 Q
b11100 P
b1000100 <
b11100 ;
1/
#5712
0/
#5754
b1000101 <
b11101 ;
b1000101 Q
b11101 P
1/
#5796
0/
#5838
b1000110 Q
b11110 P
b1000110 <
b11110 ;
1/
#5880
0/
#5922
b1000111 <
b11111 ;
b1000111 Q
b11111 P
1/
#5964
0/
#6006
b1001000 Q
b100000 P
b1001000 <
b100000 ;
1/
#6048
0/
#6090
b1001001 <
b100001 ;
b1001001 Q
b100001 P
1/
#6132
0/
#6174
b1001010 Q
b100010 P
b1001010 <
b100010 ;
1/
#6216
0/
#6258
b1001011 <
b100011 ;
b1001011 Q
b100011 P
1/
#6300
0/
#6342
b1001100 Q
b100100 P
b1001100 <
b100100 ;
1/
#6384
0/
#6426
b1001101 <
b100101 ;
b1001101 Q
b100101 P
1/
#6468
0/
#6510
b1001110 Q
b100110 P
b1001110 <
b100110 ;
1/
#6552
0/
#6594
b1001111 <
b100111 ;
b1001111 Q
b100111 P
1/
#6636
0/
#6678
b1010000 Q
0N
b0 P
b1010000 <
09
b0 ;
1/
#6720
0/
#6762
b1010001 <
b1 ;
b1010001 Q
b1 P
1/
#6804
0/
#6846
b1010010 Q
b10 P
b1010010 <
b10 ;
1/
#6888
0/
#6930
b1010011 <
b11 ;
b1010011 Q
b11 P
1/
#6972
0/
#7014
b1010100 Q
b100 P
b1010100 <
b100 ;
1/
#7056
0/
