UartStates.vh
// states of state machine
`define RESET     3'b000
`define IDLE      3'b001
`define START_BIT 3'b010
`define DATA_BITS 3'b011
`define STOP_BIT  3'b100
`define READY     3'b101 // receiver only

Uart8Transmitter.v
`include "UartStates.vh"

/*
 * 8-bit UART Transmitter
 *
 * Able to transmit 8 bits of serial data, one start bit, one stop bit
 *
 * When transmit is in progress over {out}, {busy} is driven high
 *
 * When transmit is complete, {done} is driven high for one tx clock cycle
 *
 * Capable of back-to-back transmits for full bandwidth utilization,
 *   by only changing the {in} data
 *   (*change before {done} rising edge)
 *
 * Finer control over when to start the next frame is provided by cycling
 *   the {start} input low then high
 *
 * System clock must be divided down to the baud rate, which is the
 *   {clk} input
 *
 * {TURBO_FRAMES}: performance mode versus forgiving mode:
 *
 * 0: forgiving mode:
 *    drive the mark state, aka stop bit, output high for two
 *    tx clock cycles instead of one - this way, the boundaries between
 *    data frames are distinguished in the transmitted data stream,
 *    for more robust sync between tx/rx
 *    (*sync can be re-established more quickly if it's lost)
 *    (*this mode will only have an effect in the max, back-to-back,
 *     frame transmission use case)
 *    (*this mode has no positive effect in an environment of
 *     reliably matched tx/rx baud clocks)
 *
 * 1: performance mode:
 *    drive the mark state output high for one cycle when at max rate
 *    (*this is the normal UART protocol: 80% effective data rate
 *     for 8 bits in a frame, no parity)
 */
module Uart8Transmitter #(
    parameter TURBO_FRAMES = 0
)(
    input wire clk,      // baud rate
    input wire en,
    input wire start,    // start transmission
    input wire [7:0] in, // parallel data to transmit
    output reg busy,     // transmit is in progress
    output reg done,     // end of transmission
    output reg out       // tx line for serial data
);

reg [2:0] state     = `RESET;
reg [7:0] in_data   = 8'b0; // shift reg for the data to transmit serially
reg [2:0] bit_index = 3'b0; // index for 8-bit data

always @(posedge clk) begin
    /*
     * Disable at any time in the flow
     */
    if (!en) begin
        state <= `RESET;
    end

    /*
     * State machine
     */
    case (state)
        `RESET: begin
            // state variables
            bit_index <= 3'b0;
            // outputs
            busy      <= 1'b0;
            done      <= 1'b0;
            out       <= 1'b1; // drive the line high for IDLE state
            // next state
            if (en) begin
                state <= `IDLE;
            end
        end

        `IDLE: begin
            if (start) begin
                in_data <= in; // register the input data
                state   <= `START_BIT;
            end
        end

        `START_BIT: begin
            bit_index <= 3'b0;
            busy      <= 1'b1;
            done      <= 1'b0;
            out       <= 1'b0; // send the space output, aka start bit (low)
            state     <= `DATA_BITS;
        end

        `DATA_BITS: begin // take 8 clock cycles for data bits to be sent
            // grab each input bit using a shift register: the hardware
            // realization is simple compared to routing the access
            // dynamically, i.e. using in_data[bit_index]
            in_data   <= { 1'b0, in_data[7:1] };
            out       <= in_data[0];
            // manage the state transition
            bit_index <= bit_index + 3'b1;
            if (&bit_index) begin
                // bit_index wraps around to zero
                state <= `STOP_BIT;
            end
        end

        `STOP_BIT: begin
            done              <= 1'b1; // signal the transmission stop
            out               <= 1'b1; // transition to mark state output (high)
            if (start) begin
                if (done == 1'b0) begin // this distinguishes 2 sub-states
                    in_data   <= in; // register new input data
                    if (TURBO_FRAMES) begin
                        state <= `START_BIT; // go direct to transmit
                    end else begin
                        state <= `STOP_BIT; // keep mark state one extra cycle
                    end
                end else begin // there was extra cycle within this state
                    done      <= 1'b0;
                    state     <= `START_BIT; // now go to transmit
                end
            end else begin
                state         <= `RESET;
            end
        end

        default: begin
            state <= `RESET;
        end
    endcase
end

endmodule

Uart8Receiver.v
`include "UartStates.vh"

/*
 * 8-bit UART Receiver
 *
 * Able to receive 8 bits of serial data, one start bit, one stop bit
 *
 * When receive is detected and in progress over {in}, {busy} is driven high
 *
 * When receive is complete, {done} is driven high for one serial bit cycle
 *   (aka baud interval: equal to 16 {clk} ticks)
 *
 * Output data should be taken away within one baud interval or it will be lost
 *
 * System clock must be divided down to oversampling rate times baud rate
 *   to provide the {clk} input
 *
 * (*Note this module's logic is hard-coded based on 16x oversampling rate)
 */
module Uart8Receiver (
    input wire clk,      // rx data sampling rate
    input wire en,
    input wire in,       // rx line
    output reg busy,     // transaction is in progress
    output reg done,     // end of transaction
    output reg err,      // error while receiving data
    output reg [7:0] out // the received data assembled in parallel form
);

reg [2:0] state          = `RESET;
reg [1:0] in_reg         = 2'b0; // shift reg for input signal conditioning
reg [4:0] in_hold_reg    = 5'b0; // shift reg for signal hold time checks
reg [3:0] sample_count   = 4'b0; // count ticks for 16x oversample
reg [4:0] out_hold_count = 5'b0; // count ticks before clearing output data
reg [2:0] bit_index      = 3'b0; // index for 8-bit data
reg [7:0] received_data  = 8'b0; // shift reg for the deserialized data
wire in_sample;
wire [3:0] in_prior_hold_reg;
wire [3:0] in_current_hold_reg;

/*
 * Double-register the incoming data:
 *
 * This prevents metastability problems crossing into rx clock domain
 *
 * After registering, only the in_sample wire is to be accessed - the
 *   earlier, unconditioned signal {in} must be ignored
 */
always @(posedge clk) begin
    in_reg <= { in_reg[0], in };
end

assign in_sample = in_reg[1];

/*
 * Track the incoming data for 4 rx {clk} ticks + 1, to be able to enforce a
 *   minimum hold time of 4 {clk} ticks for any rx signal
 */
always @(posedge clk) begin
    in_hold_reg <= { in_hold_reg[3:1], in_sample, in_reg[0] };
end

assign in_prior_hold_reg   = in_hold_reg[4:1];
assign in_current_hold_reg = in_hold_reg[3:0];

always @(posedge clk) begin
    /*
     * End the validity of output data after precise time of one serial bit cycle:
     *
     * Output signals from this module might as well be consistent with input
     *   rate, which is the baud rate
     *
     * This hold is for the case when detection of a next transmit cut the
     *   prior stop and ready transitions short; i.e. IDLE state has been entered
     *   direct from STOP_BIT state or READY state
     */
    if (|out_hold_count) begin
        out_hold_count     <= out_hold_count + 5'b1;
        if (out_hold_count == 5'b10000) begin // reached 16 -
            // timed output interval ends
            out_hold_count <= 5'b0;
            done           <= 1'b0;
            out            <= 8'b0;
        end
    end

    /*
     * Disable at any time in the flow
     */
    if (!en) begin
        state <= `RESET;
    end

    /*
     * State machine
     */
    case (state)
        `RESET: begin
            // state variables
            sample_count   <= 4'b0;
            out_hold_count <= 5'b0;
            received_data  <= 8'b0;
            // outputs
            busy           <= 1'b0;
            done           <= 1'b0;
            if (en && err && !in_sample) begin // in error condition already -
                // leave the output uninterrupted
                err        <= 1'b1;
            end else begin
                err        <= 1'b0;
            end
            out            <= 8'b0; // output parallel data only during {done}
            // next state
            if (en) begin
                state      <= `IDLE;
            end
        end

        `IDLE: begin
            /*
             * Accept low-going input as the trigger to start:
             *
             * Count from the first low sample, and sample again at the
             *   mid-point of a full baud interval to accept the low signal
             *
             * Then start the count for the proceeding full baud intervals
             */
            if (!in_sample) begin
                if (sample_count == 4'b0) begin
                    if (&in_prior_hold_reg || done && !err) begin
                        // meets the preceding min high hold time -
                        // note that {done} && !{err} encodes the fact that
                        // the min hold time was met earlier in STOP_BIT state
                        // or READY state
                        sample_count  <= 4'b1;
                        err           <= 1'b0;
                    end else begin
                        // this was a false start -
                        // remain in IDLE state with sample_count zero
                        err           <= 1'b1;
                    end
                end else begin
                    sample_count      <= sample_count + 4'b1;
                    if (sample_count == 4'b1100) begin // reached 12
                        // start signal meets an additional hold time
                        // of >= 4 rx ticks after its own mid-point -
                        // start new full interval count but from the mid-point
                        sample_count  <= 4'b0100;
                        busy          <= 1'b1;
                        err           <= 1'b0;
                        state         <= `START_BIT;
                    end
                end
            end else if (|sample_count) begin
                // bit did not remain low while waiting till 8 then 12 -
                // remain in IDLE state
                sample_count          <= 4'b0;
                received_data         <= 8'b0;
                err                   <= 1'b1;
            end
        end

        `START_BIT: begin
            /*
             * Wait one full baud interval to the mid-point of first bit
             */
            sample_count      <= sample_count + 4'b1;
            if (&sample_count) begin // reached 15
                // sample_count wraps around to zero
                bit_index     <= 3'b1;
                received_data <= { in_sample, 7'b0 };
                out           <= 8'b0;
                state         <= `DATA_BITS;
            end
        end

        `DATA_BITS: begin
            /*
             * Take 8 baud intervals to receive serial data
             */
            sample_count      <= sample_count + 4'b1;
            if (&sample_count) begin // reached 15 - save one more bit of data
                // store the bit using a shift register: the hardware
                // realization is simple compared to routing the bit
                // dynamically, i.e. using received_data[bit_index]
                received_data <= { in_sample, received_data[7:1] };
                // manage the state transition
                bit_index     <= bit_index + 3'b1;
                if (&bit_index) begin
                    // bit_index wraps around to zero
                    // sample_count wraps around to zero
                    state     <= `STOP_BIT;
                end
            end
        end

        `STOP_BIT: begin
            /*
             * Accept the received data if input goes high:
             *
             * If stop signal condition(s) met, drive the {done} signal high
             *   for one bit cycle
             *
             * Otherwise drive the {err} signal high for one bit cycle
             *
             * Since this baud clock may not track the transmitter baud clock
             *   precisely in reality, accept the transition to handling the
             *   next start bit any time after the stop bit mid-point
             */
            sample_count               <= sample_count + 4'b1;
            if (sample_count[3]) begin // reached 8 to 15
                if (!in_sample) begin
                    // accept that transmit has completed only if the stop
                    // signal held for a time of >= 4 rx ticks before it
                    // changed to a start signal
                    if (sample_count == 4'b1000 &&
                            &in_prior_hold_reg) begin // meets the hold time
                        // can accept the transmitted data and output it
                        sample_count   <= 4'b0;
                        out_hold_count <= 5'b1;
                        done           <= 1'b1;
                        out            <= received_data;
                        state          <= `IDLE;
                    end else if (&sample_count) begin // reached 15
                        // bit did not go high or remain high -
                        // signal {err}, continuing until condition resolved
                        sample_count   <= 4'b0;
                        received_data  <= 8'b0;
                        busy           <= 1'b0;
                        err            <= 1'b1;
                        state          <= `IDLE;
                    end
                end else begin
                    if (&in_current_hold_reg) begin // meets min high hold time
                        // can accept the transmitted data and output it
                        sample_count   <= 4'b0;
                        done           <= 1'b1;
                        out            <= received_data;
                        state          <= `READY;
                    end else if (&sample_count) begin // reached 15
                        // did not meet min high hold time -
                        // signal {err} for this transmit
                        sample_count   <= 4'b0;
                        err            <= 1'b1;
                        state          <= `READY;
                    end
                end
            end
        end

        `READY: begin
            /*
             * Wait one full bit cycle to sustain the {out} data, the
             *   {done} signal or the {err} signal
             */
            sample_count              <= sample_count + 4'b1;
            if (!err && !in_sample || &sample_count) begin
                // check if this is the change to a start signal -
                // note that in this state, in_sample has met the min high
                // hold time any time it drops to low
                // (also in these cases, namely !{err} or tick 15 special case,
                //  signaling of {done} is in progress)
                if (&sample_count) begin // reached 15, last tick, and no error
                    // (signaling of {done} is now complete)
                    if (in_sample) begin
                        // not transitioning to start bit -
                        // sample_count wraps around to zero
                        received_data <= 8'b0;
                        busy          <= 1'b0;
                    end else begin
                        // transitioning to start bit -
                        // sustain the {busy} signal high
                        sample_count  <= 4'b1;
                    end
                    done              <= 1'b0;
                    out               <= 8'b0;
                    state             <= `IDLE;
                end else begin
                    // in_sample drops from high to low
                    // (signaling of {done} continues)
                    sample_count      <= 4'b1;
                    // continue the counting
                    out_hold_count    <= sample_count + 5'b00010;
                    state             <= `IDLE;
                end
            end else if (&sample_count[3:1]) begin // reached 14 -
                // additional tick 15 comes from transiting the READY state
                // to get to the RESET state
                if (err || !in_sample) begin
                    state             <= `RESET;
                end
                // otherwise, signaling of {done} is in progress (i.e. !{err}) -
                // in this case, on tick 15, will be checking if in_sample
                // dropped from high to low on the entry to IDLE state
            end
        end

        default: begin
            state <= `RESET;
        end
    endcase
end

endmodule

BaudRateGenerator.v
/*
 * Baud rate generator to divide {CLOCK_RATE} (internal system clock) into
 *   {BAUD_RATE} tx/rx pair, with rx oversample by default 16x
 */
module BaudRateGenerator #(
    parameter CLOCK_RATE         = 100000000, // board clock (default 100MHz)
    parameter BAUD_RATE          = 9600,
    parameter RX_OVERSAMPLE_RATE = 16
)(
    input wire clk,   // board clock (*note: at the {CLOCK_RATE} rate)
    output reg rxClk, // baud rate for rx
    output reg txClk  // baud rate for tx
);

localparam RX_ACC_MAX   = CLOCK_RATE / (2 * BAUD_RATE * RX_OVERSAMPLE_RATE);
localparam TX_ACC_MAX   = CLOCK_RATE / (2 * BAUD_RATE);
localparam RX_ACC_WIDTH = $clog2(RX_ACC_MAX);
localparam TX_ACC_WIDTH = $clog2(TX_ACC_MAX);

reg [RX_ACC_WIDTH-1:0] rx_counter = 0;
reg [TX_ACC_WIDTH-1:0] tx_counter = 0;

initial begin
    rxClk = 1'b0;
    txClk = 1'b0;
end

always @(posedge clk) begin
    // rx clock
    if (rx_counter == RX_ACC_MAX[RX_ACC_WIDTH-1:0]) begin
        rx_counter <= 0;
        rxClk      <= ~rxClk;
    end else begin
        rx_counter <= rx_counter + 1'b1;
    end

    // tx clock
    if (tx_counter == TX_ACC_MAX[TX_ACC_WIDTH-1:0]) begin
        tx_counter <= 0;
        txClk      <= ~txClk;
    end else begin
        tx_counter <= tx_counter + 1'b1;
    end
end

endmodule

Uart8.v
`include "BaudRateGenerator.v"
`include "Uart8Receiver.v"
`include "Uart8Transmitter.v"

/*
 * Simple 8-bit UART realization
 *
 * Able to transmit and receive 8 bits of serial data, one start bit,
 *   one stop bit
 */
module Uart8 #(
    parameter CLOCK_RATE   = 100000000, // board clock (default 100MHz)
    parameter BAUD_RATE    = 9600,
    parameter TURBO_FRAMES = 0          // see Uart8Transmitter
)(
    input wire clk, // board clock (*note: at the {CLOCK_RATE} rate)

    // rx interface
    input wire rxEn,
    input wire rx,
    output wire rxBusy,
    output wire rxDone,
    output wire rxErr,
    output wire [7:0] out,

    // tx interface
    input wire txEn,
    input wire txStart,
    input wire [7:0] in,
    output wire txBusy,
    output wire txDone,
    output wire tx
);

// this value cannot be changed in the current implementation
localparam RX_OVERSAMPLE_RATE = 16;

wire rxClk;
wire txClk;

BaudRateGenerator #(
    .CLOCK_RATE(CLOCK_RATE),
    .BAUD_RATE(BAUD_RATE),
    .RX_OVERSAMPLE_RATE(RX_OVERSAMPLE_RATE)
) generatorInst (
    .clk(clk),
    .rxClk(rxClk),
    .txClk(txClk)
);

Uart8Receiver rxInst (
    .clk(rxClk),
    .en(rxEn),
    .in(rx),
    .busy(rxBusy),
    .done(rxDone),
    .err(rxErr),
    .out(out)
);

Uart8Transmitter #(
    .TURBO_FRAMES(TURBO_FRAMES)
) txInst (
    .clk(txClk),
    .en(txEn),
    .start(txStart),
    .in(in),
    .busy(txBusy),
    .done(txDone),
    .out(tx)
);

endmodule

tests/27a.v
`timescale 100ns/1ns
`default_nettype none

`include "Uart8.v"

module test;

localparam CLOCK_FREQ = 12000000; // Alhambra board
localparam SIM_STEP_FREQ = 1 / 0.0000001 / 2; // this sim timescale 100ns

// for the simulation timeline:
// ratio SIM_STEP_FREQ MHz / CLOCK_FREQ MHz gives the output waveform in proper time
// (*but note all clocks and the timeline are approximate due to rounding)
localparam SIM_TIMESTEP_FACTOR = SIM_STEP_FREQ / CLOCK_FREQ;

reg        clk;
reg        en_1;
reg        rx;
wire       rxBusy_2;
wire       rxDone_2;
wire       rxErr_2;
reg [7:0]  txByte_1;
wire [7:0] rxByte_2;

Uart8 #(.CLOCK_RATE(CLOCK_FREQ)) uart(
  .clk(clk),

  // rx interface
  .rxEn(en_1),
  .rx(rx),
  .rxBusy(rxBusy_2),
  .rxDone(rxDone_2),
  .rxErr(rxErr_2),
  .out(rxByte_2)

  // tx interface (unused)
);

initial clk = 1'b0;

always #SIM_TIMESTEP_FACTOR clk = ~clk;

initial begin
  $dumpfile(`DUMP_FILE_NAME);
  $dumpvars(0, test);

// #65 == 1 rx clock period (approximately) at 9600 baud
#240
  en_1 = 1'b1;
  txByte_1 = 8'b01010110;
  rx = 1'b0;

  $display("            tx data: %8b", txByte_1);
#160
  rx = 1'b1;
#360
  rx = 1'b0;
#1075 // instead of #1042, this makes transmit clock sync with receive clock (a 3% difference)
  rx = txByte_1[0];

  $display("%7.2fms | rx first bit: %1b", $realtime/10000, rx);
#1075
  rx = txByte_1[1];

  $display("%7.2fms | rx next bit: %1b", $realtime/10000, rx);
#1075
  rx = txByte_1[2];

  $display("%7.2fms | rx next bit: %1b", $realtime/10000, rx);
#1075
  rx = txByte_1[3];

  $display("%7.2fms | rx next bit: %1b", $realtime/10000, rx);
#1075
  rx = txByte_1[4];

  $display("%7.2fms | rx next bit: %1b", $realtime/10000, rx);
#1075
  rx = txByte_1[5];

  $display("%7.2fms | rx next bit: %1b", $realtime/10000, rx);
#1075
  rx = txByte_1[6];

  $display("%7.2fms | rx next bit: %1b", $realtime/10000, rx);
#1075
  rx = txByte_1[7];

  $display("%7.2fms | rx last bit: %1b", $realtime/10000, rx);
#530
  rx = 1'b1;
#1530
  rx = 1'b0;

  $display("%7.4fms | end of stop bit | start of start bit: %1b", $realtime/10000, rx);
#1075
  rx = txByte_1[0];

  $display("%7.2fms | rx first bit: %1b", $realtime/10000, rx);
#1075
  rx = txByte_1[1];

  $display("%7.2fms | rx next bit: %1b", $realtime/10000, rx);
#1075
  rx = txByte_1[2];
#50

  $finish();
end

endmodule

tests/27.vcd
$date
	Sun Jan 01 16:13:09 2023
$end
$version
	Icarus Verilog
$end
$timescale
	1ns
$end
$scope module test $end
$var wire 1 ! rxErr_2 $end
$var wire 1 " rxDone_2 $end
$var wire 8 # rxByte_2 [7:0] $end
$var wire 1 $ rxBusy_2 $end
$var reg 1 % clk $end
$var reg 1 & en_1 $end
$var reg 1 ' rx $end
$var reg 8 ( txByte_1 [7:0] $end
$scope module uart $end
$var wire 1 % clk $end
$var wire 8 ) in [7:0] $end
$var wire 1 ' rx $end
$var wire 1 & rxEn $end
$var wire 1 * txEn $end
$var wire 1 + txStart $end
$var wire 1 , txDone $end
$var wire 1 - txClk $end
$var wire 1 . txBusy $end
$var wire 1 / tx $end
$var wire 1 ! rxErr $end
$var wire 1 " rxDone $end
$var wire 1 0 rxClk $end
$var wire 1 $ rxBusy $end
$var wire 8 1 out [7:0] $end
$scope module generatorInst $end
$var wire 1 % clk $end
$var reg 1 0 rxClk $end
$var reg 6 2 rx_counter [5:0] $end
$var reg 1 - txClk $end
$var reg 10 3 tx_counter [9:0] $end
$upscope $end
$scope module rxInst $end
$var wire 1 0 clk $end
$var wire 1 & en $end
$var wire 1 ' in $end
$var wire 1 4 in_sample $end
$var wire 4 5 in_prior_hold_reg [3:0] $end
$var wire 4 6 in_current_hold_reg [3:0] $end
$var reg 3 7 bit_index [2:0] $end
$var reg 1 $ busy $end
$var reg 1 " done $end
$var reg 1 ! err $end
$var reg 5 8 in_hold_reg [4:0] $end
$var reg 2 9 in_reg [1:0] $end
$var reg 8 : out [7:0] $end
$var reg 5 ; out_hold_count [4:0] $end
$var reg 8 < received_data [7:0] $end
$var reg 4 = sample_count [3:0] $end
$var reg 3 > state [2:0] $end
$upscope $end
$scope module txInst $end
$var wire 1 - clk $end
$var wire 1 * en $end
$var wire 8 ? in [7:0] $end
$var wire 1 + start $end
$var reg 3 @ bit_index [2:0] $end
$var reg 1 . busy $end
$var reg 1 , done $end
$var reg 8 A in_data [7:0] $end
$var reg 1 / out $end
$var reg 3 B state [2:0] $end
$upscope $end
$upscope $end
$upscope $end
$enddefinitions $end
#0
$dumpvars
b0 B
b0 A
b0 @
bz ?
b0 >
b0 =
b0 <
b0 ;
bx :
b0 9
b0 8
b0 7
b0 6
b0 5
04
b0 3
b0 2
bx 1
00
x/
x.
0-
x,
z+
z*
bz )
bx (
x'
x&
0%
x$
bx #
x"
x!
$end
#42
b1 3
b1 2
1%
#84
0%
#126
b10 3
b10 2
1%
#168
0%
#210
b11 3
b11 2
1%
#252
0%
#294
b100 3
b100 2
1%
#336
0%
#378
b101 3
b101 2
1%
#420
0%
#462
b110 3
b110 2
1%
#504
0%
#546
b111 3
b111 2
1%
#588
0%
#630
b1000 3
b1000 2
1%
#672
0%
#714
b1001 3
b1001 2
1%
#756
0%
#798
b1010 3
b1010 2
1%
#840
0%
#882
b1011 3
b1011 2
1%
#924
0%
#966
b1100 3
b1100 2
1%
#1008
0%
#1050
b1101 3
b1101 2
1%
#1092
0%
#1134
b1110 3
b1110 2
1%
#1176
0%
#1218
b1111 3
b1111 2
1%
#1260
0%
#1302
b10000 3
b10000 2
1%
#1344
0%
#1386
b10001 3
b10001 2
1%
#1428
0%
#1470
b10010 3
b10010 2
1%
#1512
0%
#1554
b10011 3
b10011 2
1%
#1596
0%
#1638
b10100 3
b10100 2
1%
#1680
0%
#1722
b10101 3
b10101 2
1%
#1764
0%
#1806
b10110 3
b10110 2
1%
#1848
0%
#1890
b10111 3
b10111 2
1%
#1932
0%
#1974
b11000 3
b11000 2
1%
#2016
0%
#2058
b11001 3
b11001 2
1%
#2100
0%
#2142
b11010 3
b11010 2
1%
#2184
0%
#2226
b11011 3
b11011 2
1%
#2268
0%
#2310
b11100 3
b11100 2
1%
#2352
0%
#2394
b11101 3
b11101 2
1%
#2436
0%
#2478
b11110 3
b11110 2
1%
#2520
0%
#2562
b11111 3
b11111 2
1%
#2604
0%
#2646
b100000 3
b100000 2
1%
#2688
0%
#2730
b100001 3
b100001 2
1%
#2772
0%
#2814
b100010 3
b100010 2
1%
#2856
0%
#2898
b100011 3
b100011 2
1%
#2940
0%
#2982
b100100 3
b100100 2
1%
#3024
0%
#3066
b100101 3
b100101 2
1%
#3108
0%
#3150
b100110 3
b100110 2
1%
#3192
0%
#3234
b100111 3
b100111 2
1%
#3276
0%
#3318
b0x 9
b0 #
b0 1
b0 :
0!
0"
0$
b101000 3
10
b0 2
1%
#3360
0%
#3402
b101001 3
b1 2
1%
#3444
0%
#3486
b101010 3
b10 2
1%
#3528
0%
#3570
b101011 3
b11 2
1%
#3612
0%
#3654
b101100 3
b100 2
1%
#3696
0%
#3738
b101101 3
b101 2
1%
#3780
0%
#3822
b101110 3
b110 2
1%
#3864
0%
#3906
b101111 3
b111 2
1%
#3948
0%
#3990
b110000 3
b1000 2
1%
#4032
0%
#4074
b110001 3
b1001 2
1%
#4116
0%
#4158
b110010 3
b1010 2
1%
#4200
0%
#4242
b110011 3
b1011 2
1%
#4284
0%
#4326
b110100 3
b1100 2
1%
#4368
0%
#4410
b110101 3
b1101 2
1%
#4452
0%
#4494
b110110 3
b1110 2
1%
#4536
0%
#4578
b110111 3
b1111 2
1%
#4620
0%
#4662
b111000 3
b10000 2
1%
#4704
0%
#4746
b111001 3
b10001 2
1%
#4788
0%
#4830
b111010 3
b10010 2
1%
#4872
0%
#4914
b111011 3
b10011 2
1%
#4956
0%
#4998
b111100 3
b10100 2
1%
#5040
0%
#5082
b111101 3
b10101 2
1%
#5124
0%
#5166
b111110 3
b10110 2
1%
#5208
0%
#5250
b111111 3
b10111 2
1%
#5292
0%
#5334
b1000000 3
b11000 2
1%
#5376
0%
#5418
b1000001 3
b11001 2
1%
#5460
0%
#5502
b1000010 3
b11010 2
1%
#5544
0%
#5586
b1000011 3
b11011 2
1%
#5628
0%
#5670
b1000100 3
b11100 2
1%
#5712
0%
#5754
b1000101 3
b11101 2
1%
#5796
0%
#5838
b1000110 3
b11110 2
1%
#5880
0%
#5922
b1000111 3
b11111 2
1%
#5964
0%
#6006
b1001000 3
b100000 2
1%
#6048
0%
#6090
b1001001 3
b100001 2
1%
#6132
0%
#6174
b1001010 3
b100010 2
1%
#6216
0%
#6258
b1001011 3
b100011 2
1%
#6300
0%
#6342
b1001100 3
b100100 2
1%
#6384
0%
#6426
b1001101 3
b100101 2
1%
#6468
0%
#6510
b1001110 3
b100110 2
1%
#6552
0%
#6594
b1001111 3
b100111 2
1%
#6636
0%
#6678
b1010000 3
00
b0 2
1%
#6720
0%
#6762
b1010001 3
b1 2
1%
#6804
0%
#6846
b1010010 3
b10 2
1%
#6888
0%
#6930
b1010011 3
b11 2
1%
#6972
0%
#7014
b1010100 3
b100 2
1%
#7056
0%
#7098
b1010101 3
b101 2
1%
#7140
0%
#7182
b1010110 3
b110 2
1%
#7224
0%
#7266
b1010111 3
b111 2
1%
#7308
0%
#7350
b1011000 3
b1000 2
1%
#7392
0%
#7434
b1011001 3
b1001 2
1%
#7476
0%
#7518
b1011010 3
b1010 2
1%
#7560
0%
#7602
b1011011 3
b1011 2
1%
#7644
0%
#7686
b1011100 3
b1100 2
1%
#7728
0%
#7770
b1011101 3
b1101 2
1%
#7812
0%
#7854
b1011110 3
b1110 2
1%
#7896
0%
#7938
b1011111 3
b1111 2
1%
#7980
0%
#8022
b1100000 3
b10000 2
1%
#8064
0%
#8106
b1100001 3
b10001 2
1%
#8148
0%
#8190
b1100010 3
b10010 2
1%
#8232
0%
#8274
b1100011 3
b10011 2
1%
#8316
0%
#8358
b1100100 3
b10100 2
1%
#8400
0%
#8442
b1100101 3
b10101 2
1%
#8484
0%
#8526
b1100110 3
b10110 2
1%
#8568
0%
#8610
b1100111 3
b10111 2
1%
#8652
0%
#8694
b1101000 3
b11000 2
1%
#8736
0%
#8778
b1101001 3
b11001 2
1%
#8820
0%
#8862
b1101010 3
b11010 2
1%
#8904
0%
#8946
b1101011 3
b11011 2
1%
#8988
0%
#9030
b1101100 3
b11100 2
1%
#9072
0%
#9114
b1101101 3
b11101 2
1%
#9156
0%
#9198
b1101110 3
b11110 2
1%
#9240
0%
#9282
b1101111 3
b11111 2
1%
#9324
0%
#9366
b1110000 3
b100000 2
1%
#9408
0%
#9450
b1110001 3
b100001 2
1%
#9492
0%
#9534
b1110010 3
b100010 2
1%
#9576
0%
#9618
b1110011 3
b100011 2
1%
#9660
0%
#9702
b1110100 3
b100100 2
1%
#9744
0%
#9786
b1110101 3
b100101 2
1%
#9828
0%
#9870
b1110110 3
b100110 2
1%
#9912
0%
#9954
b1110111 3
b100111 2
1%
#9996
0%
#10038
b0x 6
x4
b0x 8
bx 9
b1111000 3
10
b0 2
1%
#10080
0%
#10122
b1111001 3
b1 2
1%
#10164
0%
#10206
b1111010 3
b10 2
1%
#10248
0%
#10290
b1111011 3
b11 2
1%
#10332
0%
#10374
b1111100 3
b100 2
1%
#10416
0%
#10458
b1111101 3
b101 2
1%
#10500
0%
#10542
b1111110 3
b110 2
1%
#10584
0%
#10626
b1111111 3
b111 2
1%
#10668
0%
#10710
b10000000 3
b1000 2
1%
#10752
0%
#10794
b10000001 3
b1001 2
1%
#10836
0%
#10878
b10000010 3
b1010 2
1%
#10920
0%
#10962
b10000011 3
b1011 2
1%
#11004
0%
#11046
b10000100 3
b1100 2
1%
#11088
0%
#11130
b10000101 3
b1101 2
1%
#11172
0%
#11214
b10000110 3
b1110 2
1%
#11256
0%
#11298
b10000111 3
b1111 2
1%
#11340
0%
#11382
b10001000 3
b10000 2
1%
#11424
0%
#11466
b10001001 3
b10001 2
1%
#11508
0%
#11550
b10001010 3
b10010 2
1%
#11592
0%
#11634
b10001011 3
b10011 2
1%
#11676
0%
#11718
b10001100 3
b10100 2
1%
#11760
0%
#11802
b10001101 3
b10101 2
1%
#11844
0%
#11886
b10001110 3
b10110 2
1%
#11928
0%
#11970
b10001111 3
b10111 2
1%
#12012
0%
#12054
b10010000 3
b11000 2
1%
#12096
0%
#12138
b10010001 3
b11001 2
1%
#12180
0%
#12222
b10010010 3
b11010 2
1%
#12264
0%
#12306
b10010011 3
b11011 2
1%
#12348
0%
#12390
b10010100 3
b11100 2
1%
#12432
0%
#12474
b10010101 3
b11101 2
1%
#12516
0%
#12558
b10010110 3
b11110 2
1%
#12600
0%
#12642
b10010111 3
b11111 2
1%
#12684
0%
#12726
b10011000 3
b100000 2
1%
#12768
0%
#12810
b10011001 3
b100001 2
1%
#12852
0%
#12894
b10011010 3
b100010 2
1%
#12936
0%
#12978
b10011011 3
b100011 2
1%
#13020
0%
#13062
b10011100 3
b100100 2
1%
#13104
0%
#13146
b10011101 3
b100101 2
1%
#13188
0%
#13230
b10011110 3
b100110 2
1%
#13272
0%
#13314
b10011111 3
b100111 2
1%
#13356
0%
#13398
b10100000 3
00
b0 2
1%
#13440
0%
#13482
b10100001 3
b1 2
1%
#13524
0%
#13566
b10100010 3
b10 2
1%
#13608
0%
#13650
b10100011 3
b11 2
1%
#13692
0%
#13734
b10100100 3
b100 2
1%
#13776
0%
#13818
b10100101 3
b101 2
1%
#13860
0%
#13902
b10100110 3
b110 2
1%
#13944
0%
#13986
b10100111 3
b111 2
1%
#14028
0%
#14070
b10101000 3
b1000 2
1%
#14112
0%
#14154
b10101001 3
b1001 2
1%
#14196
0%
#14238
b10101010 3
b1010 2
1%
#14280
0%
#14322
b10101011 3
b1011 2
1%
#14364
0%
#14406
b10101100 3
b1100 2
1%
#14448
0%
#14490
b10101101 3
b1101 2
1%
#14532
0%
#14574
b10101110 3
b1110 2
1%
#14616
0%
#14658
b10101111 3
b1111 2
1%
#14700
0%
#14742
b10110000 3
b10000 2
1%
#14784
0%
#14826
b10110001 3
b10001 2
1%
#14868
0%
#14910
b10110010 3
b10010 2
1%
#14952
0%
#14994
b10110011 3
b10011 2
1%
#15036
0%
#15078
b10110100 3
b10100 2
1%
#15120
0%
#15162
b10110101 3
b10101 2
1%
#15204
0%
#15246
b10110110 3
b10110 2
1%
#15288
0%
#15330
b10110111 3
b10111 2
1%
#15372
0%
#15414
b10111000 3
b11000 2
1%
#15456
0%
#15498
b10111001 3
b11001 2
1%
#15540
0%
#15582
b10111010 3
b11010 2
1%
#15624
0%
#15666
b10111011 3
b11011 2
1%
#15708
0%
#15750
b10111100 3
b11100 2
1%
#15792
0%
#15834
b10111101 3
b11101 2
1%
#15876
0%
#15918
b10111110 3
b11110 2
1%
#15960
0%
#16002
b10111111 3
b11111 2
1%
#16044
0%
#16086
b11000000 3
b100000 2
1%
#16128
0%
#16170
b11000001 3
b100001 2
1%
#16212
0%
#16254
b11000010 3
b100010 2
1%
#16296
0%
#16338
b11000011 3
b100011 2
1%
#16380
0%
#16422
b11000100 3
b100100 2
1%
#16464
0%
#16506
b11000101 3
b100101 2
1%
#16548
0%
#16590
b11000110 3
b100110 2
1%
#16632
0%
#16674
b11000111 3
b100111 2
1%
#16716
0%
#16758
b0x 5
b0xx 6
b0xx 8
b11001000 3
10
b0 2
1%
#16800
0%
#16842
b11001001 3
b1 2
1%
#16884
0%
